{
    "element": "shoji:entity",
    "self": "/api/datasets/41bba0/",
    "catalogs": {
        "batches": "/api/datasets/41bba0/batches/",
        "users": "/api/datasets/41bba0/users/",
        "variables": "/api/datasets/41bba0/variables/",
        "actions": "/api/datasets/41bba0/actions/",
        "savepoints": "/api/datasets/41bba0/savepoints/",
        "boxdata": "/api/datasets/41bba0/boxdata/",
        "filters": "/api/datasets/41bba0/filters/",
        "multitables": "/api/datasets/41bba0/multitables/",
        "forks": "/api/datasets/41bba0/forks/",
        "permissions": "/api/datasets/41bba0/permissions/",
        "joins": "/api/datasets/41bba0/joins/",
        "decks": "/api/datasets/41bba0/decks/",
        "parent": "/api/datasets/",
        "variables_private": "/api/datasets/41bba0/variables/private/"
    },
    "fragments": {
        "state": "/api/datasets/41bba0/state/",
        "exclusion": "/api/datasets/41bba0/exclusion/",
        "stream": "/api/datasets/41bba0/stream/",
        "settings": "/api/datasets/41bba0/settings/",
        "pk": "/api/datasets/41bba0/pk/",
        "table": "/api/datasets/41bba0/table/",
        "preferences": "/api/datasets/41bba0/preferences/"
    },
    "views": {
        "cube": "/api/datasets/41bba0/cube/",
        "export": "/api/datasets/41bba0/export/",
        "summary": "/api/datasets/41bba0/summary/",
        "applied_filters": "/api/datasets/41bba0/filters/applied/"
    },
    "description": "Detail for a given dataset",
    "body": {
        "size": {
            "rows": 1634,
            "unfiltered_rows": 1634,
            "columns": 23
        },
        "current_editor_name": "Gordon Shotwell",
        "owner_name": "Gordon Shotwell",
        "maintainer": "/api/users/7bbff9/",
        "name": "Fork of stackoverflow_survey",
        "end_date": null,
        "modification_time": "2018-05-14T16:51:26.094000",
        "access_time": "1970-01-01T00:00:00",
        "notes": "",
        "current_editor": "/api/users/7bbff9/",
        "creation_time": "2018-05-14T16:51:26.081000",
        "archived": false,
        "start_date": null,
        "streaming": "no",
        "app_settings": {
            "crunch": {
                "discarded_to_hidden": true,
                "deleted_rogue_vp": true
            }
        },
        "owner": "/api/users/7bbff9/",
        "permissions": {
            "edit": true,
            "admin": true,
            "change_permissions": true,
            "view": true
        },
        "is_published": true,
        "id": "41bba0",
        "description": ""
    },
    "orders": {
        "variables_weights": "/api/datasets/41bba0/variables/weights/",
        "variables_hier": "/api/datasets/41bba0/variables/hier/",
        "variables_personal": "/api/datasets/41bba0/variables/personal/"
    },
    "urls": {
        "owner_url": "/api/users/7bbff9/",
        "editor_url": "/api/users/7bbff9/",
        "user_url": "/api/users/7bbff9/"
    }
}
